LICENSE
README.md
setup.py
test/test_refund.py
test/test_transaction_completion_service.py
test/test_transaction_iframe_service.py
test/test_transaction_lightbox_service.py
test/test_transaction_payment_page_service.py
test/test_transaction_service.py
whitelabelmachinename/__init__.py
whitelabelmachinename/api_client.py
whitelabelmachinename/configuration.py
whitelabelmachinename/encryption_util.py
whitelabelmachinename/rest.py
whitelabelmachinename.egg-info/PKG-INFO
whitelabelmachinename.egg-info/SOURCES.txt
whitelabelmachinename.egg-info/dependency_links.txt
whitelabelmachinename.egg-info/requires.txt
whitelabelmachinename.egg-info/top_level.txt
whitelabelmachinename/api/__init__.py
whitelabelmachinename/api/account_service_api.py
whitelabelmachinename/api/analytics_query_service_api.py
whitelabelmachinename/api/application_user_service_api.py
whitelabelmachinename/api/bank_account_service_api.py
whitelabelmachinename/api/bank_transaction_service_api.py
whitelabelmachinename/api/card_processing_service_api.py
whitelabelmachinename/api/charge_attempt_service_api.py
whitelabelmachinename/api/charge_bank_transaction_service_api.py
whitelabelmachinename/api/charge_flow_level_payment_link_service_api.py
whitelabelmachinename/api/charge_flow_level_service_api.py
whitelabelmachinename/api/charge_flow_service_api.py
whitelabelmachinename/api/condition_type_service_api.py
whitelabelmachinename/api/country_service_api.py
whitelabelmachinename/api/country_state_service_api.py
whitelabelmachinename/api/currency_bank_account_service_api.py
whitelabelmachinename/api/currency_service_api.py
whitelabelmachinename/api/customer_address_service_api.py
whitelabelmachinename/api/customer_comment_service_api.py
whitelabelmachinename/api/customer_service_api.py
whitelabelmachinename/api/debt_collection_case_service_api.py
whitelabelmachinename/api/debt_collector_configuration_service_api.py
whitelabelmachinename/api/debt_collector_service_api.py
whitelabelmachinename/api/delivery_indication_service_api.py
whitelabelmachinename/api/document_template_service_api.py
whitelabelmachinename/api/document_template_type_service_api.py
whitelabelmachinename/api/external_transfer_bank_transaction_service_api.py
