Metadata-Version: 2.1
Name: whitelabelmachinename
Version: 4.1.0
Summary: SDK that allows you to access WhiteLabelName
Author: Wallee AG
License: Apache-2.0
Keywords: whitelabelmachinename,Payment,Payment Integration
Classifier: Intended Audience :: Developers
Classifier: Intended Audience :: Financial and Insurance Industry
Classifier: License :: OSI Approved :: Apache Software License
Classifier: Natural Language :: English
Classifier: Operating System :: OS Independent
Classifier: Programming Language :: Python :: 3
Classifier: Topic :: Office/Business :: Financial :: Point-Of-Sale
Requires-Python: >=3.7
License-File: LICENSE
Requires-Dist: certifi>=14.05.14
Requires-Dist: six>=1.10
Requires-Dist: python_dateutil>=2.8.2
Requires-Dist: setuptools>=68.0.0
Requires-Dist: urllib3>=2.0.7
Requires-Dist: cryptography>=2.0
